{
  "cards": [
    {
      "id": "CRD-1",
      "title": "My Card 1",
      "text": "This is my card 1"
    },
    {
      "id": "CRD-2",
      "title": "My Card 2",
      "text": "This is my card 2"
    },
    {
      "id": "CRD-3",
      "title": "My Card 3",
      "text": "This is my card 3"
    },
    {
      "id": "CRD-4",
      "title": "My Card 4",
      "text": "This is my card 4"
    },
    {
      "id": "CRD-5",
      "title": "My Card 5",
      "text": "This is my card 5"
    }
  ]
}
